marsguard/__init__.py
marsguard/example_usage.py
marsguard/exceptions.py
marsguard/schemas.py
marsguard/sdk.py
marsguard-0.2.2.dist-info/METADATA
marsguard-0.2.2.dist-info/WHEEL
marsguard-0.2.2.dist-info/top_level.txt
marsguard-0.2.2.dist-info/RECORD
