Metadata-Version: 2.4
Name: marsguard
Version: 0.2.2
Summary: Modular Python SDK for generating guardrails via the MARSGuard backend API.
Author-email: Anandakrishnan M S <i.am.anandakrishnan.m.s@gmail.com>, Mandvi Shukla <mandvishukla20@gmail.com>, Swaraj Prakash Farakate <swarajfarakate1203@gmail.com>, Ramanagouda N Hosmani <ramangoudanh@gmail.com>
Keywords: guardrail,sdk,llm,safety,policy,prompt
Classifier: Programming Language :: Python :: 3
Classifier: Programming Language :: Python :: 3 :: Only
Classifier: Programming Language :: Python :: 3.9
Classifier: Operating System :: OS Independent
Classifier: Intended Audience :: Developers
Classifier: Topic :: Software Development :: Libraries
Classifier: Topic :: Utilities
Requires-Python: >=3.9
Requires-Dist: pydantic<3.0,>=2.0
Requires-Dist: requests<3.0,>=2.28
Provides-Extra: dev
Requires-Dist: build>=1.0; extra == "dev"
Requires-Dist: twine>=4.0; extra == "dev"
